{
  "case_97": {
    "sentence": "They had already left the building.",
    "expected": {
      "main_slots": {
        "S": "They",
        "Aux": "had",
        "M2": "already",
        "V": "left",
        "O1": "the building"
      },
      "sub_slots": {}
    },
    "actual": {
      "success": true,
      "text": "They had already left the building.",
      "main_slots": {
        "Aux": "had",
        "S": "They",
        "V": "left",
        "O1": "the building",
        "M2": "already"
      },
      "sub_slots": {},
      "metadata": {
        "controller": "central",
        "primary_handler": "modal",
        "collaboration": [
          "adverb"
        ],
        "modal_info": {
          "has_modal": true,
          "modal_type": "perfect_auxiliary",
          "auxiliary": "had",
          "main_verb": null,
          "is_question": false,
          "is_negative": false,
          "structure_type": "perfect"
        },
        "confidence": 0.9
      },
      "ordered_slots": {
        "2": "had",
        "1": "They",
        "4": "left",
        "5": "the building",
        "3": "already"
      }
    },
    "match": true
  }
}